prometheus_fastapi_instrumentator/__init__.py
prometheus_fastapi_instrumentator/instrumentation.py
prometheus_fastapi_instrumentator/metrics.py
prometheus_fastapi_instrumentator/middleware.py
prometheus_fastapi_instrumentator/py.typed
prometheus_fastapi_instrumentator/routing.py
prometheus_fastapi_instrumentator-5.11.0.dist-info/LICENSE
prometheus_fastapi_instrumentator-5.11.0.dist-info/WHEEL
prometheus_fastapi_instrumentator-5.11.0.dist-info/METADATA
prometheus_fastapi_instrumentator-5.11.0.dist-info/RECORD
