Metadata-Version: 2.1
Name: prometheus-fastapi-instrumentator
Version: 5.11.0
Summary: Instrument your FastAPI with Prometheus metrics.
Home-page: https://github.com/trallnag/prometheus-fastapi-instrumentator
License: ISC
Keywords: prometheus,instrumentation,fastapi,exporter,metrics
Author: Tim Schwenke
Author-email: tim@trallnag.com
Requires-Python: >=3.7.0,<4.0.0
Classifier: License :: OSI Approved
Classifier: Programming Language :: Python :: 3
Classifier: Programming Language :: Python :: 3.7
Classifier: Programming Language :: Python :: 3.8
Classifier: Programming Language :: Python :: 3.9
Classifier: Programming Language :: Python :: 3.10
Classifier: Programming Language :: Python :: 3.11
Requires-Dist: fastapi (>=0.38.1,<1.0.0)
Requires-Dist: prometheus-client (>=0.8.0,<1.0.0)
Project-URL: Repository, https://github.com/trallnag/prometheus-fastapi-instrumentator
